hsmodels/__init__.py
hsmodels/namespaces.py
hsmodels/utils.py
hsmodels/schemas/__init__.py
hsmodels/schemas/aggregations.py
hsmodels/schemas/base_models.py
hsmodels/schemas/enums.py
hsmodels/schemas/fields.py
hsmodels/schemas/languages_iso.py
hsmodels/schemas/resource.py
hsmodels/schemas/root_validators.py
hsmodels/schemas/validators.py
hsmodels/schemas/rdf/__init__.py
hsmodels/schemas/rdf/aggregations.py
hsmodels/schemas/rdf/fields.py
hsmodels/schemas/rdf/resource.py
hsmodels/schemas/rdf/root_validators.py
hsmodels/schemas/rdf/validators.py
hsmodels-1.0.4.dist-info/LICENSE.txt
hsmodels-1.0.4.dist-info/METADATA
hsmodels-1.0.4.dist-info/WHEEL
hsmodels-1.0.4.dist-info/top_level.txt
hsmodels-1.0.4.dist-info/RECORD
