Metadata-Version: 2.1
Name: hsmodels
Version: 1.0.4
Summary: Pydantic models for HydroShare metadata
Home-page: https://github.com/hydroshare/hsmodels
Author: Scott Black
Author-email: sblack@cuahsi.org
License: MIT
Classifier: Programming Language :: Python :: 3
Classifier: Programming Language :: Python :: 3.6
Classifier: Programming Language :: Python :: 3.7
Classifier: Programming Language :: Python :: 3.8
Classifier: Programming Language :: Python :: 3.9
Requires-Python: >=3.9
License-File: LICENSE.txt
Requires-Dist: rdflib <6.0.0
Requires-Dist: pydantic ==2.7.*
Requires-Dist: email-validator
